noos_pyk/__init__.py
noos_pyk/clients/__init__.py
noos_pyk/clients/auth.py
noos_pyk/clients/base.py
noos_pyk/clients/http.py
noos_pyk/clients/json.py
noos_pyk/clients/ws.py
noos_pyk/py.typed
noos_pyk-0.0.14.dist-info/LICENSE
noos_pyk-0.0.14.dist-info/METADATA
noos_pyk-0.0.14.dist-info/WHEEL
noos_pyk-0.0.14.dist-info/RECORD
