Metadata-Version: 2.1
Name: noos-pyk
Version: 0.0.14
Summary: A simple, yet useful Python toolkit
Home-page: https://github.com/noosenergy/noos-python-kit
License: MIT
Author: Noos Energy
Author-email: contact@noos.energy
Requires-Python: >=3.12,<4.0
Classifier: Development Status :: 5 - Production/Stable
Classifier: Intended Audience :: Developers
Classifier: License :: OSI Approved :: MIT License
Classifier: Operating System :: OS Independent
Classifier: Programming Language :: Python :: 3
Classifier: Programming Language :: Python :: 3.12
Classifier: Programming Language :: Python :: 3.13
Classifier: Typing :: Typed
Provides-Extra: websocket
Requires-Dist: requests
Requires-Dist: websocket-client ; extra == "websocket"
